{
  "dyeColor": "black",
  "maxHealth": {
    "isSizeSquared": true,
    "resultMultiplier": 7
  },
  "armor": {"sizeMultiplier": 5},
  "armorToughness": {},
  "attackDamage": {
    "resultModifier": 4
  },
  "jumpDelay": {
    "sizeMultiplier": 0,
    "resultModifier": 5,
    "resultRandomModifierBound": 10
  },
  "experienceValue": {
    "sizeMultiplier": 1.5
  },
  "squishParticleData": {
    "typeString": "BLOCK",
    "resourceLocation": "minecraft:obsidian"
  },
  "slimeSpawnData": [
    {
      "minPackSize": 1,
      "maxPackSize": 1,
      "spawnWeight": 1,
      "biomes": [
        "END"
      ]
    }
  ]
}